razorpay/__init__.py
razorpay/ca-bundle.crt
razorpay/client.py
razorpay/errors.py
razorpay/constants/__init__.py
razorpay/constants/error_code.py
razorpay/constants/http_status_code.py
razorpay/constants/url.py
razorpay/resources/__init__.py
razorpay/resources/account.py
razorpay/resources/addon.py
razorpay/resources/base.py
razorpay/resources/card.py
razorpay/resources/customer.py
razorpay/resources/fund_account.py
razorpay/resources/iin.py
razorpay/resources/invoice.py
razorpay/resources/item.py
razorpay/resources/order.py
razorpay/resources/payment.py
razorpay/resources/payment_link.py
razorpay/resources/plan.py
razorpay/resources/product.py
razorpay/resources/qrcode.py
razorpay/resources/refund.py
razorpay/resources/registration_link.py
razorpay/resources/settlement.py
razorpay/resources/stakeholder.py
razorpay/resources/subscription.py
razorpay/resources/token.py
razorpay/resources/transfer.py
razorpay/resources/virtual_account.py
razorpay/resources/webhook.py
razorpay/utility/__init__.py
razorpay/utility/utility.py
razorpay-1.4.1.dist-info/LICENSE
razorpay-1.4.1.dist-info/METADATA
razorpay-1.4.1.dist-info/WHEEL
razorpay-1.4.1.dist-info/top_level.txt
razorpay-1.4.1.dist-info/RECORD
